{
    "name": "python3-kolibri-explore-plugin",
    "buildsystem": "simple",
    "build-commands": [
        "pip3 install --exists-action=i --no-index --find-links=\"file://${PWD}\" --prefix=${FLATPAK_DEST} kolibri-explore-plugin",
        "mkdir -p \"${FLATPAK_DEST}/share/endless-key\"",
        "cp -R apps-bundle -t \"${ENDLESS_KEY_DATA_DIR}\"",
        "cp -R loading-screen -t \"${ENDLESS_KEY_DATA_DIR}\""
    ],
    "sources": [
        {
            "type": "file",
            "url": "https://github.com/endlessm/kolibri-explore-plugin/releases/download/v7.8.0/kolibri_explore_plugin-7.8.0-py3-none-any.whl",
            "sha256": "c363eef27505793c4a8a3eca614b2e4397a949745327cd26044c665dd262c814",
            "x-checker-data": {
                "type": "json",
                "url": "https://api.github.com/repos/endlessm/kolibri-explore-plugin/releases/latest",
                "version-query": ".tag_name | sub(\"^[vV]\"; \"\")",
                "url-query": ".assets[] | select(.name==\"kolibri_explore_plugin-\" + $version + \"-py3-none-any.whl\") | .browser_download_url",
                "versions": {
                    "<": "8.0.0"
                }
            }
        },
        {
            "type": "archive",
            "url": "https://github.com/endlessm/kolibri-explore-plugin/releases/download/v7.8.0/apps-bundle.zip",
            "sha256": "afb15028a9692a6e68d63e98ac8e0cd085f5b458ad9c923fca07d7081772c7ed",
            "dest": "apps-bundle",
            "x-checker-data": {
                "type": "json",
                "url": "https://api.github.com/repos/endlessm/kolibri-explore-plugin/releases/latest",
                "version-query": ".tag_name | sub(\"^[vV]\"; \"\")",
                "url-query": ".assets[] | select(.name==\"apps-bundle.zip\") | .browser_download_url",
                "versions": {
                    "<": "8.0.0"
                }
            }
        },
        {
            "type": "archive",
            "url": "https://github.com/endlessm/kolibri-explore-plugin/releases/download/v7.8.0/loading-screen.zip",
            "sha256": "e4e1fea3510b4bd40844f4b31254d91adac12effbda23f38f52e163ab3e0d6b8",
            "strip-components": 0,
            "dest": "loading-screen",
            "x-checker-data": {
                "type": "json",
                "url": "https://api.github.com/repos/endlessm/kolibri-explore-plugin/releases/latest",
                "version-query": ".tag_name | sub(\"^[vV]\"; \"\")",
                "url-query": ".assets[] | select(.name==\"loading-screen.zip\") | .browser_download_url",
                "versions": {
                    "<": "8.0.0"
                }
            }
        }
    ]
}
